automate_docs-0.0.7.dist-info/licenses/LICENSE
automate_readme/__init__.py
automate_readme/main.py
automate_readme/request.py
automate_docs-0.0.7.dist-info/METADATA
automate_docs-0.0.7.dist-info/WHEEL
automate_docs-0.0.7.dist-info/entry_points.txt
automate_docs-0.0.7.dist-info/top_level.txt
automate_docs-0.0.7.dist-info/RECORD
